[
  {
    "text": "开发计划",
    "items": [
      { "text": "计划总览", "link": "/roadmap/" },
      { "text": "后端计划 Phase1", "link": "/roadmap/backend-dev-plan" },
      { "text": "后端计划 Phase2", "link": "/roadmap/backend-dev-plan-phase2" },
      { "text": "账户删除功能", "link": "/roadmap/account-deletion" },
      { "text": "审计日志导出", "link": "/roadmap/auditlog-export" },
      { "text": "用户头像上传", "link": "/roadmap/avatar-upload" },
      { "text": "批量用户导入", "link": "/roadmap/batch-import" },
      { "text": "用户列表导出", "link": "/roadmap/user-export" },
      { "text": "角色列表导出", "link": "/roadmap/role-export" },
      { "text": "菜单列表导出", "link": "/roadmap/menu-export" },
      { "text": "密码强度指示器", "link": "/roadmap/password-strength" },
      { "text": "复制到剪贴板", "link": "/roadmap/clipboard-copy" },
      { "text": "确认对话框组件", "link": "/roadmap/confirm-dialog" },
      { "text": "数据仪表盘", "link": "/roadmap/dashboard" },
      { "text": "防抖搜索", "link": "/roadmap/debounce-search" },
      { "text": "面包屑导航", "link": "/roadmap/breadcrumb" },
      { "text": "空状态组件", "link": "/roadmap/empty-state" },
      { "text": "加载遮罩组件", "link": "/roadmap/loading-overlay" },
      { "text": "键盘快捷键", "link": "/roadmap/keyboard-shortcuts" },
      { "text": "页面过渡动画", "link": "/roadmap/page-transition" },
      { "text": "日期时间格式化", "link": "/roadmap/date-utils" },
      { "text": "回到顶部按钮", "link": "/roadmap/back-to-top" },
      { "text": "骨架屏加载", "link": "/roadmap/skeleton-loader" },
      { "text": "数字格式化", "link": "/roadmap/number-utils" },
      { "text": "存储工具", "link": "/roadmap/storage-utils" },
      { "text": "表单验证工具", "link": "/roadmap/form-validation" },
      { "text": "字符串工具函数", "link": "/roadmap/string-utils" },
      { "text": "窗口尺寸检测", "link": "/roadmap/window-size" },
      { "text": "交叉观察器", "link": "/roadmap/intersection-observer" },
      { "text": "点击外部检测", "link": "/roadmap/click-outside" },
      { "text": "异步状态管理", "link": "/roadmap/async-state" },
      { "text": "网络状态检测", "link": "/roadmap/network-status" },
      { "text": "全屏 API", "link": "/roadmap/fullscreen" },
      { "text": "滚动锁定", "link": "/roadmap/scroll-lock" },
      { "text": "焦点陷阱", "link": "/roadmap/focus-trap" },
      { "text": "拖拽排序", "link": "/roadmap/draggable" },
      { "text": "表单状态管理", "link": "/roadmap/form-state" },
      { "text": "倒计时", "link": "/roadmap/countdown" },
      { "text": "事件总线", "link": "/roadmap/event-bus" },
      { "text": "历史记录", "link": "/roadmap/history" },
      { "text": "平台检测", "link": "/roadmap/platform" },
      { "text": "限流工具", "link": "/roadmap/throttle" },
      { "text": "数组工具", "link": "/roadmap/array-utils" },
      { "text": "对象工具", "link": "/roadmap/object-utils" },
      { "text": "ID 生成工具", "link": "/roadmap/id-utils" },
      { "text": "颜色工具", "link": "/roadmap/color-utils" },
      { "text": "URL 工具", "link": "/roadmap/url-utils" },
      { "text": "DOM 工具", "link": "/roadmap/dom-utils" },
      { "text": "Cookie 工具", "link": "/roadmap/cookie-utils" },
      { "text": "类型工具", "link": "/roadmap/type-utils" },
      { "text": "Timer Composable", "link": "/roadmap/timer-composable" },
      { "text": "Permission Composable", "link": "/roadmap/permission-composable" },
      { "text": "Mouse Composable", "link": "/roadmap/mouse-composable" },
      { "text": "Geolocation Composable", "link": "/roadmap/geolocation-composable" },
      { "text": "Preferences Composable", "link": "/roadmap/preferences-composable" },
      { "text": "Title Composable", "link": "/roadmap/title-composable" },
      { "text": "WebSocket Composable", "link": "/roadmap/websocket-composable" },
      { "text": "EventSource Composable", "link": "/roadmap/eventsource-composable" },
      { "text": "BroadcastChannel Composable", "link": "/roadmap/broadcast-channel-composable" },
      { "text": "Image Composable", "link": "/roadmap/image-composable" },
      { "text": "Clone Composable", "link": "/roadmap/clone-composable" },
      { "text": "Fetch Composable", "link": "/roadmap/fetch-composable" },
      { "text": "VModel Composable", "link": "/roadmap/vmodel-composable" },
      { "text": "SWR Composable", "link": "/roadmap/swr-composable" },
      { "text": "Watch Composable", "link": "/roadmap/watch-composable" },
      { "text": "Computed Composable", "link": "/roadmap/computed-composable" },
      { "text": "Ref Composable", "link": "/roadmap/ref-composable" },
      { "text": "Reactive Composable", "link": "/roadmap/reactive-composable" },
      { "text": "Lifecycle Composable", "link": "/roadmap/lifecycle-composable" },
      { "text": "Provide Composable", "link": "/roadmap/provide-composable" },
      { "text": "Component Composable", "link": "/roadmap/component-composable" },
      { "text": "Transition Composable", "link": "/roadmap/transition-composable" },
      { "text": "Queue Composable", "link": "/roadmap/queue-composable" },
      { "text": "Media Composable", "link": "/roadmap/media-composable" }
    ]
  }
]
